<?xml version="1.0" encoding="UTF-8"?>
<bundle>
  <Signin>
    <welcome>ようこそ</welcome>
    <login>ログイン</login>
    <logout>ログアウト</logout>
    <language>
      <en>英語に切り替える</en>
      <fr>フランス語に切り替える</fr>
    </language>
    <register>登録</register>
  </Signin>
  <Toolbar>
    <SkipToContent>コンテンツへ飛びます</SkipToContent>
    <SiteMap>サイトマップ</SiteMap>
    <Accessibility>アクセシビリティ</Accessibility>
    <NormalSize>通常サイズ</NormalSize>
    <MediumSize>中サイズ</MediumSize>
    <LargeSize>大サイズ</LargeSize>
    <NormalContrast>通常のコントラスト</NormalContrast>
    <HighContrast>高コントラスト</HighContrast>
    <Search>検索</Search>
  </Toolbar>
  <Logo>
    <GoHome>ホームへ飛ぶ</GoHome>
  </Logo>
  <acme>
    <label>ACME テンプレート</label>
  </acme>  
  <WAIPortal>
    <label>サンプル ウェブサイト</label>
  </WAIPortal>
</bundle>
