<?xml version="1.0" encoding="UTF-8"?><sv:node xmlns:nt="http://www.jcp.org/jcr/nt/1.0" xmlns:xcmis="http://www.exoplatform.com/jcr/xcmis/1.0" xmlns:lr="http://www.exoplatform.org/liveroom/1.0" xmlns:tkn="http://www.gatein.org/jcr/token/1.0/" xmlns:webdav="http://www.exoplatform.org/jcr/webdav" xmlns:xs="http://www.w3.org/2001/XMLSchema" xmlns:rh="www.vn.vnn" xmlns:gtn="http://www.gatein.org/jcr/gatein/1.0/" xmlns:jcr="http://www.jcp.org/jcr/1.0" xmlns:wsrp="http://www.gatein.org/jcr/wsrp/1.0/" xmlns:sv="http://www.jcp.org/jcr/sv/1.0" xmlns:fn="http://www.w3.org/2005/xpath-functions" xmlns:metadata="http://www.exoplatform.com/jcr/metadata/1.1/" xmlns:dc="http://purl.org/dc/elements/1.1/" xmlns:app="http://www.gatein.org/jcr/application-registry/1.0/" xmlns:Re="http://www.exoplatform.com/jcr/Re/1.1/" xmlns:cmis="http://www.exoplatform.com/jcr/cmis/1.0" xmlns:lgn="http://www.gatein.org/jcr/autologin/1.0/" xmlns:mop="http://www.gatein.org/jcr/mop/1.0/" xmlns:fn_old="http://www.w3.org/2004/10/xpath-functions" xmlns:mix="http://www.jcp.org/jcr/mix/1.0" xmlns:publication="http://www.exoplatform.com/jcr/publication/1.1/" xmlns:exo="http://www.exoplatform.com/jcr/exo/1.0" xmlns:Fwd="http://www.exoplatform.com/jcr/Fwd/1.1/" xmlns:pc="http://www.gatein.org/jcr/pc/1.0/" xmlns:rma="http://www.rma.com/jcr/" xmlns:kfx="http://www.exoplatform.com/jcr/kfx/1.1/" xmlns:rep="internal" xmlns:portlet="http://www.gatein.org/jcr/portlet/1.0/" sv:name="Searchbox"><sv:property sv:name="jcr:primaryType" sv:type="Name"><sv:value>exo:webContent</sv:value></sv:property><sv:property sv:name="jcr:mixinTypes" sv:type="Name"><sv:value>exo:owneable</sv:value><sv:value>exo:datetime</sv:value><sv:value>exo:linkable</sv:value><sv:value>mix:votable</sv:value><sv:value>mix:commentable</sv:value><sv:value>exo:modify</sv:value></sv:property><sv:property sv:name="jcr:uuid" sv:type="String"><sv:value>38fcbe637f000001004fb894a4a9ccd9</sv:value></sv:property><sv:property sv:name="exo:dateCreated" sv:type="Date"><sv:value>2009-08-21T01:06:11.090+07:00</sv:value></sv:property><sv:property sv:name="exo:dateModified" sv:type="Date"><sv:value>2010-08-02T10:18:54.425+07:00</sv:value></sv:property><sv:property sv:name="exo:lastModifiedDate" sv:type="Date"><sv:value>2010-08-02T10:20:15.422+07:00</sv:value></sv:property><sv:property sv:name="exo:lastModifier" sv:type="String"><sv:value>__system</sv:value></sv:property><sv:property sv:name="exo:links" sv:type="String"><sv:value/></sv:property><sv:property sv:name="exo:owner" sv:type="String"><sv:value>root</sv:value></sv:property><sv:property sv:name="exo:summary" sv:type="String"><sv:value>&lt;br /&gt;</sv:value></sv:property><sv:property sv:name="exo:title" sv:type="String"><sv:value>ACME Searchbox</sv:value></sv:property><sv:property sv:name="exo:voteTotal" sv:type="Long"><sv:value>0</sv:value></sv:property><sv:property sv:name="exo:voteTotalOfLang" sv:type="Long"><sv:value>0</sv:value></sv:property><sv:property sv:name="exo:votingRate" sv:type="Double"><sv:value>0.0</sv:value></sv:property><sv:property sv:name="jcr:created" sv:type="Date"><sv:value>2009-08-21T01:06:11.062+07:00</sv:value></sv:property><sv:node sv:name="js"><sv:property sv:name="jcr:primaryType" sv:type="Name"><sv:value>exo:jsFolder</sv:value></sv:property><sv:property sv:name="jcr:mixinTypes" sv:type="Name"><sv:value>exo:owneable</sv:value><sv:value>exo:datetime</sv:value><sv:value>mix:votable</sv:value><sv:value>mix:commentable</sv:value></sv:property><sv:property sv:name="exo:dateCreated" sv:type="Date"><sv:value>2009-08-21T01:06:11.162+07:00</sv:value></sv:property><sv:property sv:name="exo:dateModified" sv:type="Date"><sv:value>2009-08-21T01:06:11.169+07:00</sv:value></sv:property><sv:property sv:name="exo:owner" sv:type="String"><sv:value>root</sv:value></sv:property><sv:property sv:name="exo:voteTotal" sv:type="Long"><sv:value>0</sv:value></sv:property><sv:property sv:name="exo:voteTotalOfLang" sv:type="Long"><sv:value>0</sv:value></sv:property><sv:property sv:name="exo:votingRate" sv:type="Double"><sv:value>0.0</sv:value></sv:property><sv:property sv:name="jcr:created" sv:type="Date"><sv:value>2009-08-21T01:06:11.131+07:00</sv:value></sv:property><sv:node sv:name="default.js"><sv:property sv:name="jcr:primaryType" sv:type="Name"><sv:value>nt:file</sv:value></sv:property><sv:property sv:name="jcr:mixinTypes" sv:type="Name"><sv:value>exo:owneable</sv:value><sv:value>exo:jsFile</sv:value><sv:value>exo:datetime</sv:value><sv:value>mix:votable</sv:value><sv:value>mix:commentable</sv:value><sv:value>exo:modify</sv:value></sv:property><sv:property sv:name="jcr:uuid" sv:type="String"><sv:value>38fcbeee7f0000010092b2b8e1441e70</sv:value></sv:property><sv:property sv:name="exo:active" sv:type="Boolean"><sv:value>true</sv:value></sv:property><sv:property sv:name="exo:dateCreated" sv:type="Date"><sv:value>2009-08-21T01:06:11.276+07:00</sv:value></sv:property><sv:property sv:name="exo:dateModified" sv:type="Date"><sv:value>2009-08-21T01:06:11.283+07:00</sv:value></sv:property><sv:property sv:name="exo:lastModifiedDate" sv:type="Date"><sv:value>2010-08-02T10:18:54.425+07:00</sv:value></sv:property><sv:property sv:name="exo:lastModifier" sv:type="String"><sv:value>root</sv:value></sv:property><sv:property sv:name="exo:owner" sv:type="String"><sv:value>root</sv:value></sv:property><sv:property sv:name="exo:presentationType" sv:type="String"><sv:value>exo:jsFile</sv:value></sv:property><sv:property sv:name="exo:priority" sv:type="Long"><sv:value>0</sv:value></sv:property><sv:property sv:name="exo:voteTotal" sv:type="Long"><sv:value>0</sv:value></sv:property><sv:property sv:name="exo:voteTotalOfLang" sv:type="Long"><sv:value>0</sv:value></sv:property><sv:property sv:name="exo:votingRate" sv:type="Double"><sv:value>0.0</sv:value></sv:property><sv:property sv:name="jcr:created" sv:type="Date"><sv:value>2009-08-21T01:06:11.190+07:00</sv:value></sv:property><sv:node sv:name="jcr:content"><sv:property sv:name="jcr:primaryType" sv:type="Name"><sv:value>nt:resource</sv:value></sv:property><sv:property sv:name="jcr:mixinTypes" sv:type="Name"><sv:value>exo:owneable</sv:value><sv:value>exo:datetime</sv:value><sv:value>dc:elementSet</sv:value><sv:value>mix:votable</sv:value><sv:value>mix:commentable</sv:value></sv:property><sv:property sv:name="jcr:uuid" sv:type="String"><sv:value>38fcbf617f00000100cda064e74c4e1e</sv:value></sv:property><sv:property sv:name="exo:dateCreated" sv:type="Date"><sv:value>2009-08-21T01:06:11.336+07:00</sv:value></sv:property><sv:property sv:name="exo:dateModified" sv:type="Date"><sv:value>2009-08-21T01:06:11.345+07:00</sv:value></sv:property><sv:property sv:name="exo:internalUse" sv:type="Boolean"><sv:value>false</sv:value></sv:property><sv:property sv:name="exo:owner" sv:type="String"><sv:value>root</sv:value></sv:property><sv:property sv:name="exo:voteTotal" sv:type="Long"><sv:value>0</sv:value></sv:property><sv:property sv:name="exo:voteTotalOfLang" sv:type="Long"><sv:value>0</sv:value></sv:property><sv:property sv:name="exo:votingRate" sv:type="Double"><sv:value>0.0</sv:value></sv:property><sv:property sv:name="jcr:data" sv:type="Binary"><sv:value>ZVhvLnJlcXVpcmUoImVYby53Y20uZnJvbnRvZmZpY2UucHVibGljLlNlYXJjaCIsICIvZVhvV0NNUmVzb3VyY2VzL2phdmFzY3JpcHQvIik7</sv:value></sv:property><sv:property sv:name="jcr:encoding" sv:type="String"><sv:value>UTF-8</sv:value></sv:property><sv:property sv:name="jcr:lastModified" sv:type="Date"><sv:value>2010-08-02T00:00:00.000+07:00</sv:value></sv:property><sv:property sv:name="jcr:mimeType" sv:type="String"><sv:value>application/x-javascript</sv:value></sv:property></sv:node></sv:node></sv:node><sv:node sv:name="css"><sv:property sv:name="jcr:primaryType" sv:type="Name"><sv:value>exo:cssFolder</sv:value></sv:property><sv:property sv:name="jcr:mixinTypes" sv:type="Name"><sv:value>exo:owneable</sv:value><sv:value>exo:datetime</sv:value><sv:value>mix:votable</sv:value><sv:value>mix:commentable</sv:value></sv:property><sv:property sv:name="exo:dateCreated" sv:type="Date"><sv:value>2009-08-21T01:06:11.439+07:00</sv:value></sv:property><sv:property sv:name="exo:dateModified" sv:type="Date"><sv:value>2009-08-21T01:06:11.446+07:00</sv:value></sv:property><sv:property sv:name="exo:owner" sv:type="String"><sv:value>root</sv:value></sv:property><sv:property sv:name="exo:voteTotal" sv:type="Long"><sv:value>0</sv:value></sv:property><sv:property sv:name="exo:voteTotalOfLang" sv:type="Long"><sv:value>0</sv:value></sv:property><sv:property sv:name="exo:votingRate" sv:type="Double"><sv:value>0.0</sv:value></sv:property><sv:property sv:name="jcr:created" sv:type="Date"><sv:value>2009-08-21T01:06:11.409+07:00</sv:value></sv:property><sv:node sv:name="default.css"><sv:property sv:name="jcr:primaryType" sv:type="Name"><sv:value>nt:file</sv:value></sv:property><sv:property sv:name="jcr:mixinTypes" sv:type="Name"><sv:value>exo:owneable</sv:value><sv:value>exo:cssFile</sv:value><sv:value>exo:datetime</sv:value><sv:value>mix:votable</sv:value><sv:value>mix:commentable</sv:value><sv:value>exo:modify</sv:value></sv:property><sv:property sv:name="jcr:uuid" sv:type="String"><sv:value>38fcc0037f000001009ecde148a0179f</sv:value></sv:property><sv:property sv:name="exo:active" sv:type="Boolean"><sv:value>true</sv:value></sv:property><sv:property sv:name="exo:dateCreated" sv:type="Date"><sv:value>2009-08-21T01:06:11.558+07:00</sv:value></sv:property><sv:property sv:name="exo:dateModified" sv:type="Date"><sv:value>2009-08-21T01:06:11.566+07:00</sv:value></sv:property><sv:property sv:name="exo:lastModifiedDate" sv:type="Date"><sv:value>2010-08-02T10:18:54.394+07:00</sv:value></sv:property><sv:property sv:name="exo:lastModifier" sv:type="String"><sv:value>root</sv:value></sv:property><sv:property sv:name="exo:owner" sv:type="String"><sv:value>root</sv:value></sv:property><sv:property sv:name="exo:presentationType" sv:type="String"><sv:value>exo:cssFile</sv:value></sv:property><sv:property sv:name="exo:priority" sv:type="Long"><sv:value>0</sv:value></sv:property><sv:property sv:name="exo:voteTotal" sv:type="Long"><sv:value>0</sv:value></sv:property><sv:property sv:name="exo:voteTotalOfLang" sv:type="Long"><sv:value>0</sv:value></sv:property><sv:property sv:name="exo:votingRate" sv:type="Double"><sv:value>0.0</sv:value></sv:property><sv:property sv:name="jcr:created" sv:type="Date"><sv:value>2009-08-21T01:06:11.470+07:00</sv:value></sv:property><sv:node sv:name="jcr:content"><sv:property sv:name="jcr:primaryType" sv:type="Name"><sv:value>nt:resource</sv:value></sv:property><sv:property sv:name="jcr:mixinTypes" sv:type="Name"><sv:value>exo:owneable</sv:value><sv:value>exo:datetime</sv:value><sv:value>dc:elementSet</sv:value><sv:value>mix:votable</sv:value><sv:value>mix:commentable</sv:value></sv:property><sv:property sv:name="jcr:uuid" sv:type="String"><sv:value>38fcc07b7f00000100ad978d2b7adc09</sv:value></sv:property><sv:property sv:name="exo:dateCreated" sv:type="Date"><sv:value>2009-08-21T01:06:11.620+07:00</sv:value></sv:property><sv:property sv:name="exo:dateModified" sv:type="Date"><sv:value>2009-08-21T01:06:11.626+07:00</sv:value></sv:property><sv:property sv:name="exo:internalUse" sv:type="Boolean"><sv:value>false</sv:value></sv:property><sv:property sv:name="exo:owner" sv:type="String"><sv:value>root</sv:value></sv:property><sv:property sv:name="exo:voteTotal" sv:type="Long"><sv:value>0</sv:value></sv:property><sv:property sv:name="exo:voteTotalOfLang" sv:type="Long"><sv:value>0</sv:value></sv:property><sv:property sv:name="exo:votingRate" sv:type="Double"><sv:value>0.0</sv:value></sv:property><sv:property sv:name="jcr:data" sv:type="Binary"><sv:value>LmtleXdvcmQgewogIGJhY2tncm91bmQ6IHdoaXRlIHVybCgnL3BvcnRhbC9yZXN0L2pjci9yZXBvc2l0b3J5L2NvbGxhYm9yYXRpb24vc2l0ZXMgY29udGVudC9saXZlL2FjbWUvd2ViIGNvbnRlbnRzL3NpdGUgYXJ0aWZhY3RzL1NlYXJjaGJveC9tZWRpYXMvaW1hZ2VzL1NlYXJjaC5naWYnKSBuby1yZXBlYXQgNHB4IGNlbnRlcjsKICAtbW96LWJvcmRlci1yYWRpdXM6M3B4OwogIC13ZWJraXQtYm9yZGVyLXJhZGl1czozcHg7CiAgaGVpZ2h0OiAxOHB4OwogIHdpZHRoOiAxMjBweDsKICBib3JkZXI6IG5vbmU7CiAgcGFkZGluZy1sZWZ0OiAyMHB4Owp9</sv:value></sv:property><sv:property sv:name="jcr:encoding" sv:type="String"><sv:value>UTF-8</sv:value></sv:property><sv:property sv:name="jcr:lastModified" sv:type="Date"><sv:value>2010-08-02T00:00:00.000+07:00</sv:value></sv:property><sv:property sv:name="jcr:mimeType" sv:type="String"><sv:value>text/css</sv:value></sv:property></sv:node></sv:node></sv:node><sv:node sv:name="medias"><sv:property sv:name="jcr:primaryType" sv:type="Name"><sv:value>exo:multimediaFolder</sv:value></sv:property><sv:property sv:name="jcr:mixinTypes" sv:type="Name"><sv:value>exo:owneable</sv:value><sv:value>exo:datetime</sv:value><sv:value>mix:votable</sv:value><sv:value>mix:commentable</sv:value></sv:property><sv:property sv:name="exo:dateCreated" sv:type="Date"><sv:value>2009-08-21T01:06:11.711+07:00</sv:value></sv:property><sv:property sv:name="exo:dateModified" sv:type="Date"><sv:value>2009-08-21T01:06:11.718+07:00</sv:value></sv:property><sv:property sv:name="exo:owner" sv:type="String"><sv:value>root</sv:value></sv:property><sv:property sv:name="exo:voteTotal" sv:type="Long"><sv:value>0</sv:value></sv:property><sv:property sv:name="exo:voteTotalOfLang" sv:type="Long"><sv:value>0</sv:value></sv:property><sv:property sv:name="exo:votingRate" sv:type="Double"><sv:value>0.0</sv:value></sv:property><sv:node sv:name="images"><sv:property sv:name="jcr:primaryType" sv:type="Name"><sv:value>nt:folder</sv:value></sv:property><sv:property sv:name="jcr:mixinTypes" sv:type="Name"><sv:value>exo:owneable</sv:value><sv:value>exo:datetime</sv:value><sv:value>mix:votable</sv:value><sv:value>mix:commentable</sv:value></sv:property><sv:property sv:name="exo:dateCreated" sv:type="Date"><sv:value>2009-08-21T01:06:11.770+07:00</sv:value></sv:property><sv:property sv:name="exo:dateModified" sv:type="Date"><sv:value>2009-08-21T01:06:11.777+07:00</sv:value></sv:property><sv:property sv:name="exo:owner" sv:type="String"><sv:value>root</sv:value></sv:property><sv:property sv:name="exo:voteTotal" sv:type="Long"><sv:value>0</sv:value></sv:property><sv:property sv:name="exo:voteTotalOfLang" sv:type="Long"><sv:value>0</sv:value></sv:property><sv:property sv:name="exo:votingRate" sv:type="Double"><sv:value>0.0</sv:value></sv:property><sv:property sv:name="jcr:created" sv:type="Date"><sv:value>2009-08-21T01:06:11.738+07:00</sv:value></sv:property><sv:node sv:name="illustration"><sv:property sv:name="jcr:primaryType" sv:type="Name"><sv:value>nt:file</sv:value></sv:property><sv:property sv:name="jcr:mixinTypes" sv:type="Name"><sv:value>exo:owneable</sv:value><sv:value>exo:datetime</sv:value><sv:value>mix:referenceable</sv:value><sv:value>mix:votable</sv:value><sv:value>mix:commentable</sv:value><sv:value>exo:modify</sv:value></sv:property><sv:property sv:name="jcr:uuid" sv:type="String"><sv:value>38fcc14e7f000001000ee9aa1af0fe10</sv:value></sv:property><sv:property sv:name="exo:dateCreated" sv:type="Date"><sv:value>2009-08-21T01:06:11.854+07:00</sv:value></sv:property><sv:property sv:name="exo:dateModified" sv:type="Date"><sv:value>2009-08-21T01:06:11.860+07:00</sv:value></sv:property><sv:property sv:name="exo:lastModifiedDate" sv:type="Date"><sv:value>2010-08-02T10:18:54.410+07:00</sv:value></sv:property><sv:property sv:name="exo:lastModifier" sv:type="String"><sv:value>root</sv:value></sv:property><sv:property sv:name="exo:owner" sv:type="String"><sv:value>root</sv:value></sv:property><sv:property sv:name="exo:voteTotal" sv:type="Long"><sv:value>0</sv:value></sv:property><sv:property sv:name="exo:voteTotalOfLang" sv:type="Long"><sv:value>0</sv:value></sv:property><sv:property sv:name="exo:votingRate" sv:type="Double"><sv:value>0.0</sv:value></sv:property><sv:property sv:name="jcr:created" sv:type="Date"><sv:value>2009-08-21T01:06:11.798+07:00</sv:value></sv:property><sv:node sv:name="jcr:content"><sv:property sv:name="jcr:primaryType" sv:type="Name"><sv:value>nt:resource</sv:value></sv:property><sv:property sv:name="jcr:mixinTypes" sv:type="Name"><sv:value>exo:owneable</sv:value><sv:value>exo:datetime</sv:value><sv:value>dc:elementSet</sv:value><sv:value>mix:votable</sv:value><sv:value>mix:commentable</sv:value></sv:property><sv:property sv:name="jcr:uuid" sv:type="String"><sv:value>38fcc1a77f0000010011c078a25ad906</sv:value></sv:property><sv:property sv:name="exo:dateCreated" sv:type="Date"><sv:value>2009-08-21T01:06:11.918+07:00</sv:value></sv:property><sv:property sv:name="exo:dateModified" sv:type="Date"><sv:value>2009-08-21T01:06:11.924+07:00</sv:value></sv:property><sv:property sv:name="exo:internalUse" sv:type="Boolean"><sv:value>false</sv:value></sv:property><sv:property sv:name="exo:owner" sv:type="String"><sv:value>root</sv:value></sv:property><sv:property sv:name="exo:voteTotal" sv:type="Long"><sv:value>0</sv:value></sv:property><sv:property sv:name="exo:voteTotalOfLang" sv:type="Long"><sv:value>0</sv:value></sv:property><sv:property sv:name="exo:votingRate" sv:type="Double"><sv:value>0.0</sv:value></sv:property><sv:property sv:name="jcr:data" sv:type="Binary"><sv:value/></sv:property><sv:property sv:name="jcr:encoding" sv:type="String"><sv:value>UTF-8</sv:value></sv:property><sv:property sv:name="jcr:lastModified" sv:type="Date"><sv:value>2010-08-02T00:00:00.000+07:00</sv:value></sv:property><sv:property sv:name="jcr:mimeType" sv:type="String"><sv:value/></sv:property></sv:node></sv:node><sv:node sv:name="Search.gif"><sv:property sv:name="jcr:primaryType" sv:type="Name"><sv:value>nt:file</sv:value></sv:property><sv:property sv:name="jcr:mixinTypes" sv:type="Name"><sv:value>exo:modify</sv:value><sv:value>exo:owneable</sv:value><sv:value>exo:datetime</sv:value><sv:value>mix:i18n</sv:value><sv:value>mix:votable</sv:value><sv:value>mix:commentable</sv:value><sv:value>mix:referenceable</sv:value><sv:value>exo:rss-enable</sv:value></sv:property><sv:property sv:name="jcr:uuid" sv:type="String"><sv:value>30d1d2f0c0a8014a00e2fcd53af287b6</sv:value></sv:property><sv:property sv:name="exo:dateCreated" sv:type="Date"><sv:value>2010-08-02T10:21:51.616+07:00</sv:value></sv:property><sv:property sv:name="exo:dateModified" sv:type="Date"><sv:value>2010-08-02T10:21:51.616+07:00</sv:value></sv:property><sv:property sv:name="exo:language" sv:type="String"><sv:value>en</sv:value></sv:property><sv:property sv:name="exo:lastModifiedDate" sv:type="Date"><sv:value>2010-08-02T10:21:51.725+07:00</sv:value></sv:property><sv:property sv:name="exo:lastModifier" sv:type="String"><sv:value>root</sv:value></sv:property><sv:property sv:name="exo:owner" sv:type="String"><sv:value>root</sv:value></sv:property><sv:property sv:name="exo:title" sv:type="String"><sv:value>Search.gif</sv:value></sv:property><sv:property sv:name="exo:voteTotal" sv:type="Long"><sv:value>0</sv:value></sv:property><sv:property sv:name="exo:voteTotalOfLang" sv:type="Long"><sv:value>0</sv:value></sv:property><sv:property sv:name="exo:votingRate" sv:type="Double"><sv:value>0.0</sv:value></sv:property><sv:property sv:name="jcr:created" sv:type="Date"><sv:value>2010-08-02T10:21:51.616+07:00</sv:value></sv:property><sv:node sv:name="jcr:content"><sv:property sv:name="jcr:primaryType" sv:type="Name"><sv:value>nt:resource</sv:value></sv:property><sv:property sv:name="jcr:mixinTypes" sv:type="Name"><sv:value>exo:owneable</sv:value><sv:value>exo:datetime</sv:value><sv:value>dc:elementSet</sv:value></sv:property><sv:property sv:name="jcr:uuid" sv:type="String"><sv:value>30d1d300c0a8014a013eb81747f082e4</sv:value></sv:property><sv:property sv:name="exo:dateCreated" sv:type="Date"><sv:value>2010-08-02T10:21:51.616+07:00</sv:value></sv:property><sv:property sv:name="exo:dateModified" sv:type="Date"><sv:value>2010-08-02T10:21:51.616+07:00</sv:value></sv:property><sv:property sv:name="exo:internalUse" sv:type="Boolean"><sv:value>false</sv:value></sv:property><sv:property sv:name="exo:owner" sv:type="String"><sv:value>root</sv:value></sv:property><sv:property sv:name="jcr:data" sv:type="Binary"><sv:value>R0lGODlhEAAQANUAAO7u7vPz83t7e/j4+JaWlvv7+5WVlezs7OLi4peXl5mZmfr6+sTExI2Njc/Pz7+/v8zMzJiYmPn5+e/v7+Pj46Wlpejo6PLy8qurq7q6uouLi8bGxoyMjLS0tI6OjsXFxY+Pj+Dg4IiIiLi4uLW1tcDAwOTk5MHBwaqqqvz8/P39/f7+/nd3d////wAAAAAAAAAAAAAAAAAAAAAAAAAAAAAAAAAAAAAAAAAAAAAAAAAAAAAAAAAAAAAAAAAAAAAAACH5BAAAAAAALAAAAAAQABAAAAaEwJZwSCwaj6skcVJSCBSnyTEFwLCuVxTAqHqwCAwEw8B6cBOsT2AQ2LASqqJKwAKkWlSW4E4sEFgQQxBfBUUpGSwRDgMOESwkfEMqJhVYWBwBRhIIIwYCBh0aLB6ZRCsSFwcWBwAIDSwgpS0rsyoqKbYDFA0iB0emuiELtL9CKwXDxcVBADs=</sv:value></sv:property><sv:property sv:name="jcr:encoding" sv:type="String"><sv:value>UTF-8</sv:value></sv:property><sv:property sv:name="jcr:lastModified" sv:type="Date"><sv:value>2010-08-02T10:21:51.600+07:00</sv:value></sv:property><sv:property sv:name="jcr:mimeType" sv:type="String"><sv:value>image/gif</sv:value></sv:property></sv:node></sv:node></sv:node><sv:node sv:name="videos"><sv:property sv:name="jcr:primaryType" sv:type="Name"><sv:value>nt:folder</sv:value></sv:property><sv:property sv:name="jcr:mixinTypes" sv:type="Name"><sv:value>exo:owneable</sv:value><sv:value>exo:datetime</sv:value><sv:value>mix:votable</sv:value><sv:value>mix:commentable</sv:value></sv:property><sv:property sv:name="exo:dateCreated" sv:type="Date"><sv:value>2009-08-21T01:06:12.017+07:00</sv:value></sv:property><sv:property sv:name="exo:dateModified" sv:type="Date"><sv:value>2009-08-21T01:06:12.024+07:00</sv:value></sv:property><sv:property sv:name="exo:owner" sv:type="String"><sv:value>root</sv:value></sv:property><sv:property sv:name="exo:voteTotal" sv:type="Long"><sv:value>0</sv:value></sv:property><sv:property sv:name="exo:voteTotalOfLang" sv:type="Long"><sv:value>0</sv:value></sv:property><sv:property sv:name="exo:votingRate" sv:type="Double"><sv:value>0.0</sv:value></sv:property><sv:property sv:name="jcr:created" sv:type="Date"><sv:value>2009-08-21T01:06:11.985+07:00</sv:value></sv:property></sv:node></sv:node><sv:node sv:name="default.html"><sv:property sv:name="jcr:primaryType" sv:type="Name"><sv:value>nt:file</sv:value></sv:property><sv:property sv:name="jcr:mixinTypes" sv:type="Name"><sv:value>exo:owneable</sv:value><sv:value>exo:datetime</sv:value><sv:value>exo:htmlFile</sv:value><sv:value>mix:votable</sv:value><sv:value>mix:commentable</sv:value><sv:value>exo:modify</sv:value></sv:property><sv:property sv:name="jcr:uuid" sv:type="String"><sv:value>38fcc2537f0000010028bf85455f2522</sv:value></sv:property><sv:property sv:name="exo:dateCreated" sv:type="Date"><sv:value>2009-08-21T01:06:12.109+07:00</sv:value></sv:property><sv:property sv:name="exo:dateModified" sv:type="Date"><sv:value>2009-08-21T01:06:12.116+07:00</sv:value></sv:property><sv:property sv:name="exo:lastModifiedDate" sv:type="Date"><sv:value>2010-08-02T10:18:54.378+07:00</sv:value></sv:property><sv:property sv:name="exo:lastModifier" sv:type="String"><sv:value>root</sv:value></sv:property><sv:property sv:name="exo:owner" sv:type="String"><sv:value>root</sv:value></sv:property><sv:property sv:name="exo:voteTotal" sv:type="Long"><sv:value>0</sv:value></sv:property><sv:property sv:name="exo:voteTotalOfLang" sv:type="Long"><sv:value>0</sv:value></sv:property><sv:property sv:name="exo:votingRate" sv:type="Double"><sv:value>0.0</sv:value></sv:property><sv:property sv:name="jcr:created" sv:type="Date"><sv:value>2009-08-21T01:06:12.059+07:00</sv:value></sv:property><sv:node sv:name="jcr:content"><sv:property sv:name="jcr:primaryType" sv:type="Name"><sv:value>nt:resource</sv:value></sv:property><sv:property sv:name="jcr:mixinTypes" sv:type="Name"><sv:value>exo:owneable</sv:value><sv:value>exo:datetime</sv:value><sv:value>dc:elementSet</sv:value><sv:value>mix:votable</sv:value><sv:value>mix:commentable</sv:value></sv:property><sv:property sv:name="jcr:uuid" sv:type="String"><sv:value>38fcc2b37f00000100200506626aecfe</sv:value></sv:property><sv:property sv:name="exo:dateCreated" sv:type="Date"><sv:value>2009-08-21T01:06:12.184+07:00</sv:value></sv:property><sv:property sv:name="exo:dateModified" sv:type="Date"><sv:value>2009-08-21T01:06:12.191+07:00</sv:value></sv:property><sv:property sv:name="exo:internalUse" sv:type="Boolean"><sv:value>false</sv:value></sv:property><sv:property sv:name="exo:owner" sv:type="String"><sv:value>root</sv:value></sv:property><sv:property sv:name="exo:voteTotal" sv:type="Long"><sv:value>0</sv:value></sv:property><sv:property sv:name="exo:voteTotalOfLang" sv:type="Long"><sv:value>0</sv:value></sv:property><sv:property sv:name="exo:votingRate" sv:type="Double"><sv:value>0.0</sv:value></sv:property><sv:property sv:name="jcr:data" sv:type="Binary"><sv:value>PGRpdiBjbGFzcz0iVUlXQ01TZWFyY2hCb3hQb3J0bGV0Ij4KPGRpdiBjbGFzcz0iTGVmdFNlYXJjaEJveCI+CjxkaXYgY2xhc3M9IlJpZ2h0U2VhcmNoQm94Ij4KPGRpdiBjbGFzcz0iQ2VudGVyU2VhcmNoQm94Ij4KPGRpdiBpZD0ic2l0ZVNlYXJjaEJveCIgY2xhc3M9InNpdGVTZWFyY2hCb3giPgo8ZGl2IGNsYXNzPSJrZXl3b3JkSW5wdXQiPjxpbnB1dCB0eXBlPSJ0ZXh0IiBuYW1lPSJrZXl3b3JkIiBvbmtleXByZXNzPSJlWG8uZWNtLlNlYXJjaFBvcnRsZXQucXVpY2tTZWFyY2hPbkVudGVyKGV2ZW50KTsiIGNsYXNzPSJrZXl3b3JkIiAvPjwvZGl2Pgo8L2Rpdj4KPGRpdj48L2Rpdj4KPC9kaXY+CjwvZGl2Pgo8L2Rpdj4KPC9kaXY+</sv:value></sv:property><sv:property sv:name="jcr:encoding" sv:type="String"><sv:value>UTF-8</sv:value></sv:property><sv:property sv:name="jcr:lastModified" sv:type="Date"><sv:value>2010-08-02T00:00:00.000+07:00</sv:value></sv:property><sv:property sv:name="jcr:mimeType" sv:type="String"><sv:value>text/html</sv:value></sv:property></sv:node></sv:node><sv:node sv:name="documents"><sv:property sv:name="jcr:primaryType" sv:type="Name"><sv:value>nt:unstructured</sv:value></sv:property><sv:property sv:name="jcr:mixinTypes" sv:type="Name"><sv:value>exo:owneable</sv:value><sv:value>exo:datetime</sv:value><sv:value>exo:documentFolder</sv:value><sv:value>mix:votable</sv:value><sv:value>mix:commentable</sv:value></sv:property><sv:property sv:name="exo:dateCreated" sv:type="Date"><sv:value>2009-08-21T01:06:12.309+07:00</sv:value></sv:property><sv:property sv:name="exo:dateModified" sv:type="Date"><sv:value>2009-08-21T01:06:12.316+07:00</sv:value></sv:property><sv:property sv:name="exo:owner" sv:type="String"><sv:value>root</sv:value></sv:property><sv:property sv:name="exo:voteTotal" sv:type="Long"><sv:value>0</sv:value></sv:property><sv:property sv:name="exo:voteTotalOfLang" sv:type="Long"><sv:value>0</sv:value></sv:property><sv:property sv:name="exo:votingRate" sv:type="Double"><sv:value>0.0</sv:value></sv:property></sv:node></sv:node>